LICENSE
MANIFEST.in
README.rst
setup.py
django_bot_crawler_blocker/__init__.py
django_bot_crawler_blocker/apps.py
django_bot_crawler_blocker/django_bot_crawler_middleware.py
django_bot_crawler_blocker.egg-info/PKG-INFO
django_bot_crawler_blocker.egg-info/SOURCES.txt
django_bot_crawler_blocker.egg-info/dependency_links.txt
django_bot_crawler_blocker.egg-info/top_level.txt