Metadata-Version: 1.1
Name: django-bot-crawler-blocker
Version: 1.0
Summary: A Django app to block the IP addresses which sends too many hits to your application
Home-page: http://www.thepythondjango.com/
Author: Anurag Rana
Author-email: anuragrana03@gmail.com
License: MIT License
Keywords: ip blocker,crawler blocker,bot blocker
Platform: UNKNOWN
Classifier: Development Status :: 5 - Production/Stable
Classifier: Environment :: Web Environment
Classifier: Framework :: Django
Classifier: Framework :: Django :: 1.10
Classifier: Intended Audience :: Developers
Classifier: License :: OSI Approved :: MIT License
Classifier: Operating System :: OS Independent
Classifier: Programming Language :: Python
Classifier: Programming Language :: Python :: 3.4
Classifier: Programming Language :: Python :: 3.5
Classifier: Programming Language :: Python :: 3.6
Classifier: Topic :: Internet :: WWW/HTTP
Classifier: Topic :: Internet :: WWW/HTTP :: Dynamic Content
